captcha/__init__.py
captcha/audio.py
captcha/image.py
captcha/py.typed
captcha/data/DroidSansMono.ttf
captcha/data/beep.wav
captcha/data/0/default.wav
captcha/data/1/default.wav
captcha/data/2/default.wav
captcha/data/3/default.wav
captcha/data/4/default.wav
captcha/data/5/default.wav
captcha/data/6/default.wav
captcha/data/7/default.wav
captcha/data/8/default.wav
captcha/data/9/default.wav
captcha-0.5.0.dist-info/LICENSE
captcha-0.5.0.dist-info/METADATA
captcha-0.5.0.dist-info/WHEEL
captcha-0.5.0.dist-info/top_level.txt
captcha-0.5.0.dist-info/RECORD
